pgame_simple/__init__.py
pgame_simple/pgame_simple.py
pgame_simple-0.1.3.dist-info/METADATA
pgame_simple-0.1.3.dist-info/WHEEL
pgame_simple-0.1.3.dist-info/licenses/LICENSE
pgame_simple-0.1.3.dist-info/RECORD
