Metadata-Version: 2.1
Name: pgame_simple
Version: 0.1.3
Summary: a framework based on pygame
Author: MRanos
License-File: LICENSE
Classifier: License :: OSI Approved :: MIT License
Classifier: Operating System :: OS Independent
Classifier: Programming Language :: Python :: 3
Requires-Python: >=3.11
